IbmDeveloperworksQuanbuJiaochengYi/README.md
IbmDeveloperworksQuanbuJiaochengYi/__init__.py
IbmDeveloperworksQuanbuJiaochengYi/__main__.py
IbmDeveloperworksQuanbuJiaochengYi/file.epub
IbmDeveloperworksQuanbuJiaochengYi/index.html
IbmDeveloperworksQuanbuJiaochengYi/css/__init__.py
IbmDeveloperworksQuanbuJiaochengYi/css/annotations.css
IbmDeveloperworksQuanbuJiaochengYi/css/main.css
IbmDeveloperworksQuanbuJiaochengYi/css/normalize.css
IbmDeveloperworksQuanbuJiaochengYi/css/popup.css
IbmDeveloperworksQuanbuJiaochengYi/font/__init__.py
IbmDeveloperworksQuanbuJiaochengYi/font/fontello.eot
IbmDeveloperworksQuanbuJiaochengYi/font/fontello.svg
IbmDeveloperworksQuanbuJiaochengYi/font/fontello.ttf
IbmDeveloperworksQuanbuJiaochengYi/font/fontello.woff
IbmDeveloperworksQuanbuJiaochengYi/img/__init__.py
IbmDeveloperworksQuanbuJiaochengYi/img/annotator-glyph-sprite.png
IbmDeveloperworksQuanbuJiaochengYi/img/annotator-icon-sprite.png
IbmDeveloperworksQuanbuJiaochengYi/img/apple-touch-icon.png
IbmDeveloperworksQuanbuJiaochengYi/img/cancelfullscreen.png
IbmDeveloperworksQuanbuJiaochengYi/img/close.png
IbmDeveloperworksQuanbuJiaochengYi/img/fullscreen.png
IbmDeveloperworksQuanbuJiaochengYi/img/loader.gif
IbmDeveloperworksQuanbuJiaochengYi/img/menu-icon.png
IbmDeveloperworksQuanbuJiaochengYi/img/save.png
IbmDeveloperworksQuanbuJiaochengYi/img/saved.png
IbmDeveloperworksQuanbuJiaochengYi/img/settings-s.png
IbmDeveloperworksQuanbuJiaochengYi/img/settings.png
IbmDeveloperworksQuanbuJiaochengYi/img/star.png
IbmDeveloperworksQuanbuJiaochengYi/js/__init__.py
IbmDeveloperworksQuanbuJiaochengYi/js/epub.js
IbmDeveloperworksQuanbuJiaochengYi/js/epub.min.js
IbmDeveloperworksQuanbuJiaochengYi/js/epub.min.map
IbmDeveloperworksQuanbuJiaochengYi/js/hooks.min.js
IbmDeveloperworksQuanbuJiaochengYi/js/hooks.min.map
IbmDeveloperworksQuanbuJiaochengYi/js/reader.js
IbmDeveloperworksQuanbuJiaochengYi/js/reader.js.map
IbmDeveloperworksQuanbuJiaochengYi/js/reader.min.js
ibm_developerworks_quanbu_jiaocheng_yi-2024.3.5.0.dist-info/METADATA
ibm_developerworks_quanbu_jiaocheng_yi-2024.3.5.0.dist-info/WHEEL
ibm_developerworks_quanbu_jiaocheng_yi-2024.3.5.0.dist-info/entry_points.txt
ibm_developerworks_quanbu_jiaocheng_yi-2024.3.5.0.dist-info/top_level.txt
ibm_developerworks_quanbu_jiaocheng_yi-2024.3.5.0.dist-info/RECORD
